arithematic_niranjan/__init__.py
arithematic_niranjan/arithematic.py
arithematic_niranjan-0.0.3.dist-info/licenses/license
arithematic_niranjan-0.0.3.dist-info/METADATA
arithematic_niranjan-0.0.3.dist-info/WHEEL
arithematic_niranjan-0.0.3.dist-info/top_level.txt
arithematic_niranjan-0.0.3.dist-info/RECORD
