Metadata-Version: 2.4
Name: arithematic_niranjan
Version: 0.0.3
Summary: Arithematic_operations
Author-email: niranjan <yvniranjanreddy@gmail.com>
License-Expression: MIT
Classifier: Programming Language :: Python :: 3
Classifier: Operating System :: OS Independent
Requires-Python: >=3.9
License-File: license
Dynamic: license-file
